vraxion/__init__.py
vraxion/__version__.py
vraxion/api.py
vraxion/middleware.py
vraxion/orm.py
vraxion/response.py
vraxion-0.1.3.dist-info/METADATA
vraxion-0.1.3.dist-info/WHEEL
vraxion-0.1.3.dist-info/top_level.txt
vraxion-0.1.3.dist-info/RECORD
