Metadata-Version: 2.1
Name: vraxion
Version: 0.1.3
Summary: Vraxion is a Python Web Framework built for learning purposes.
Home-page: UNKNOWN
Author: Michael Karotsieris
Author-email: michael.karotsieris@gmail.com
License: MIT
Platform: UNKNOWN
Classifier: Programming Language :: Python :: 3.9
Requires-Python: >=3.9.0
Requires-Dist: Jinja2 (==3.1.2)
Requires-Dist: parse (==1.12.1)
Requires-Dist: requests (==2.22.0)
Requires-Dist: requests-wsgi-adapter (==0.4.1)
Requires-Dist: WebOb (==1.8.5)
Requires-Dist: whitenoise (==4.1.4)
